{"data_non_statistical":false,"goal_meta_link":"https://unstats.un.org/sdgs/metadata/files/Metadata-16-01-01.pdf ","goal_meta_link_text":"United Nations Sustainable Development Goals Metadata (PDF 222 KB)","graph_type":"line","indicator":"16.1.1","indicator_name":"Number of victims of intentional homicide per 100,000 population, by sex and age","indicator_sort_order":"16-01-01","layout":"indicator","permalink":"/16-1-1/","published":true,"reporting_status":"complete","sdg_goal":"16","target":"Significantly reduce all forms of violence and related death rates everywhere","target_id":"16.1","graph_title":"Number of victims of intentional homicide per 100,000 population, by sex and age","un_custodian_agency":"United Nations Office on Drugs and Crime (UNODC) World Health Organization (WHO)","un_designated_tier":"1","national_data_update_url_text":"2018-12-05: see changes on GitHub","national_data_update_url":"https://github.com/open-sdg/open-sdg-data-testing/commit/201568f03c514e9061cdf0f3a9eadcf3478f995d","national_metadata_update_url_text":"2018-12-05: see changes on GitHub","national_metadata_update_url":"https://github.com/open-sdg/open-sdg-data-testing/commit/207f71d5da1a876c7a9602db6892316fe7afe6db","page_content":""}